lakefs_provider/__init__.py
lakefs_provider/example_dags/__init__.py
lakefs_provider/example_dags/lakefs-dag.py
lakefs_provider/hooks/__init__.py
lakefs_provider/hooks/lakefs_hook.py
lakefs_provider/links/__init__.py
lakefs_provider/links/lakefs_link.py
lakefs_provider/operators/__init__.py
lakefs_provider/operators/commit_operator.py
lakefs_provider/operators/create_branch_operator.py
lakefs_provider/operators/create_symlink_operator.py
lakefs_provider/operators/delete_branch_operator.py
lakefs_provider/operators/get_commit_operator.py
lakefs_provider/operators/get_object_operator.py
lakefs_provider/operators/merge_operator.py
lakefs_provider/operators/upload_operator.py
lakefs_provider/operators/with_metadata_operator.py
lakefs_provider/sensors/__init__.py
lakefs_provider/sensors/commit_sensor.py
lakefs_provider/sensors/file_sensor.py
airflow_provider_lakefs-0.48.0.dist-info/LICENSE
airflow_provider_lakefs-0.48.0.dist-info/METADATA
airflow_provider_lakefs-0.48.0.dist-info/WHEEL
airflow_provider_lakefs-0.48.0.dist-info/entry_points.txt
airflow_provider_lakefs-0.48.0.dist-info/top_level.txt
airflow_provider_lakefs-0.48.0.dist-info/RECORD
