Metadata-Version: 2.1
Name: airflow-provider-lakefs
Version: 0.48.0
Summary: A lakeFS provider package built by Treeverse.
Home-page: https://lakefs.io
Author: Treeverse
Author-email: services@treeverse.io
License: Apache License 2.0
Requires-Python: >=3.7
License-File: LICENSE
Requires-Dist: apache-airflow >=2.0
Requires-Dist: lakefs-sdk >=0.113.0.2
